LICENSE
MANIFEST.in
README.md
VERSION
requirements.txt
setup.cfg
setup.py
fastapi_toolkit/__init__.py
fastapi_toolkit/application.py
fastapi_toolkit/console_scripts.py
fastapi_toolkit/contextmanagers.py
fastapi_toolkit/logging.py
fastapi_toolkit/monitoring.py
fastapi_toolkit/redis.py
fastapi_toolkit/response.py
fastapi_toolkit/shortcuts.py
fastapi_toolkit/tasks.py
fastapi_toolkit.egg-info/PKG-INFO
fastapi_toolkit.egg-info/SOURCES.txt
fastapi_toolkit.egg-info/dependency_links.txt
fastapi_toolkit.egg-info/entry_points.txt
fastapi_toolkit.egg-info/not-zip-safe
fastapi_toolkit.egg-info/requires.txt
fastapi_toolkit.egg-info/top_level.txt
fastapi_toolkit/conf/__init__.py
fastapi_toolkit/conf/global_settings.py
fastapi_toolkit/crud/__init__.py
fastapi_toolkit/crud/base.py
fastapi_toolkit/db/__init__.py
fastapi_toolkit/db/base_class.py
fastapi_toolkit/db/expression.py
fastapi_toolkit/dependencies/__init__.py
fastapi_toolkit/dependencies/filter.py
fastapi_toolkit/dependencies/nginx.py
fastapi_toolkit/dependencies/order.py
fastapi_toolkit/dependencies/pagination.py
fastapi_toolkit/filters/__init__.py
fastapi_toolkit/filters/func.py
fastapi_toolkit/management/__init__.py
fastapi_toolkit/management/commands/__init__.py
fastapi_toolkit/management/commands/dbshell.py
fastapi_toolkit/management/commands/init_alembic.py
fastapi_toolkit/management/commands/makemigrations.py
fastapi_toolkit/management/commands/migrate.py
fastapi_toolkit/management/commands/runserver.py
fastapi_toolkit/management/commands/shell.py
fastapi_toolkit/management/commands/test.py
fastapi_toolkit/project_template/cookiecutter.json
fastapi_toolkit/project_template/{{cookiecutter.project_name}}/manage.py
fastapi_toolkit/project_template/{{cookiecutter.project_name}}/tox.ini
fastapi_toolkit/project_template/{{cookiecutter.project_name}}/sources/conf.py
fastapi_toolkit/project_template/{{cookiecutter.project_name}}/sources/main.py
fastapi_toolkit/project_template/{{cookiecutter.project_name}}/sources/alembic/README
fastapi_toolkit/project_template/{{cookiecutter.project_name}}/sources/alembic/alembic.ini
fastapi_toolkit/project_template/{{cookiecutter.project_name}}/sources/alembic/env.py
