Metadata-Version: 2.1
Name: fastapi-toolkit
Version: 0.0.20
Summary: Package for creating web app using fastapi
Home-page: https://github.com/timaakulich/fastapi_toolkit
Author: Timofey Akulich
Author-email: tima.akulich@gmail.com
License: UNKNOWN
Platform: UNKNOWN
License-File: LICENSE
